logic/__init__.py
logic/board.py
logic/game.py
logic/player.py
logic/ranking.py
logic/settings.py
tic_tac_toe_alex_p1-0.1.2.dist-info/WHEEL
tic_tac_toe_alex_p1-0.1.2.dist-info/METADATA
tic_tac_toe_alex_p1-0.1.2.dist-info/RECORD
