Metadata-Version: 2.1
Name: tic-tac-toe-alex-p1
Version: 0.1.2
Summary: Onboarding project phase 1
Author: Alexandre Meneses
Author-email: alexandre.meneses@fabamaq.com
Requires-Python: >=3.8,<4.0
Classifier: Programming Language :: Python :: 3
Classifier: Programming Language :: Python :: 3.10
Classifier: Programming Language :: Python :: 3.8
Classifier: Programming Language :: Python :: 3.9
